{
  "underlying": "JSWSTEEL",
  "rows": [
    {
      "strike": 880,
      "symbol_ce": "JSWSTEEL25NOV880CE",
      "ce_token": 24558082,
      "ce_ltp": 0,
      "ce_oi": null,
      "ce_volume": null,
      "symbol_pe": "JSWSTEEL25NOV880PE",
      "pe_token": 24558338,
      "pe_ltp": 0,
      "pe_oi": null,
      "pe_volume": null
    },
    {
      "strike": 900,
      "symbol_ce": "JSWSTEEL25OCT900CE",
      "ce_token": 25797634,
      "ce_ltp": 0,
      "ce_oi": null,
      "ce_volume": null,
      "symbol_pe": "JSWSTEEL25OCT900PE",
      "pe_token": 25798914,
      "pe_ltp": 0,
      "pe_oi": null,
      "pe_volume": null
    },
    {
      "strike": 920,
      "symbol_ce": "JSWSTEEL25NOV920CE",
      "ce_token": 24559106,
      "ce_ltp": 0,
      "ce_oi": null,
      "ce_volume": null,
      "symbol_pe": "JSWSTEEL25NOV920PE",
      "pe_token": 24559362,
      "pe_ltp": 0,
      "pe_oi": null,
      "pe_volume": null
    },
    {
      "strike": 930,
      "symbol_ce": "JSWSTEEL25OCT930CE",
      "ce_token": 24519682,
      "ce_ltp": 0,
      "ce_oi": null,
      "ce_volume": null,
      "symbol_pe": "JSWSTEEL25OCT930PE",
      "pe_token": 24519938,
      "pe_ltp": 0,
      "pe_oi": null,
      "pe_volume": null
    },
    {
      "strike": 940,
      "symbol_ce": "JSWSTEEL25NOV940CE",
      "ce_token": 24577026,
      "ce_ltp": 0,
      "ce_oi": null,
      "ce_volume": null,
      "symbol_pe": "JSWSTEEL25NOV940PE",
      "pe_token": 24577282,
      "pe_ltp": 0,
      "pe_oi": null,
      "pe_volume": null
    },
    {
      "strike": 950,
      "symbol_ce": "JSWSTEEL25OCT950CE",
      "ce_token": 24520194,
      "ce_ltp": 0,
      "ce_oi": null,
      "ce_volume": null,
      "symbol_pe": "JSWSTEEL25OCT950PE",
      "pe_token": 24520450,
      "pe_ltp": 0,
      "pe_oi": null,
      "pe_volume": null
    },
    {
      "strike": 960,
      "symbol_ce": "JSWSTEEL25NOV960CE",
      "ce_token": 24577538,
      "ce_ltp": 0,
      "ce_oi": null,
      "ce_volume": null,
      "symbol_pe": "JSWSTEEL25NOV960PE",
      "pe_token": 24577794,
      "pe_ltp": 0,
      "pe_oi": null,
      "pe_volume": null
    },
    {
      "strike": 970,
      "symbol_ce": "JSWSTEEL25OCT970CE",
      "ce_token": 24520706,
      "ce_ltp": 0,
      "ce_oi": null,
      "ce_volume": null,
      "symbol_pe": "JSWSTEEL25OCT970PE",
      "pe_token": 24520962,
      "pe_ltp": 0,
      "pe_oi": null,
      "pe_volume": null
    },
    {
      "strike": 980,
      "symbol_ce": "JSWSTEEL25NOV980CE",
      "ce_token": 24578050,
      "ce_ltp": 0,
      "ce_oi": null,
      "ce_volume": null,
      "symbol_pe": "JSWSTEEL25NOV980PE",
      "pe_token": 24578306,
      "pe_ltp": 0,
      "pe_oi": null,
      "pe_volume": null
    },
    {
      "strike": 990,
      "symbol_ce": "JSWSTEEL25OCT990CE",
      "ce_token": 24521218,
      "ce_ltp": 0,
      "ce_oi": null,
      "ce_volume": null,
      "symbol_pe": "JSWSTEEL25OCT990PE",
      "pe_token": 24521474,
      "pe_ltp": 0,
      "pe_oi": null,
      "pe_volume": null
    },
    {
      "strike": 1000,
      "symbol_ce": "JSWSTEEL25NOV1000CE",
      "ce_token": 24578562,
      "ce_ltp": 0,
      "ce_oi": null,
      "ce_volume": null,
      "symbol_pe": "JSWSTEEL25NOV1000PE",
      "pe_token": 24578818,
      "pe_ltp": 0,
      "pe_oi": null,
      "pe_volume": null
    },
    {
      "strike": 1010,
      "symbol_ce": "JSWSTEEL25OCT1010CE",
      "ce_token": 24521730,
      "ce_ltp": 0,
      "ce_oi": null,
      "ce_volume": null,
      "symbol_pe": "JSWSTEEL25OCT1010PE",
      "pe_token": 24521986,
      "pe_ltp": 0,
      "pe_oi": null,
      "pe_volume": null
    },
    {
      "strike": 1020,
      "symbol_ce": "JSWSTEEL25NOV1020CE",
      "ce_token": 24582658,
      "ce_ltp": 0,
      "ce_oi": null,
      "ce_volume": null,
      "symbol_pe": "JSWSTEEL25NOV1020PE",
      "pe_token": 24582914,
      "pe_ltp": 0,
      "pe_oi": null,
      "pe_volume": null
    },
    {
      "strike": 1030,
      "symbol_ce": "JSWSTEEL25OCT1030CE",
      "ce_token": 24522242,
      "ce_ltp": 0,
      "ce_oi": null,
      "ce_volume": null,
      "symbol_pe": "JSWSTEEL25OCT1030PE",
      "pe_token": 24522498,
      "pe_ltp": 0,
      "pe_oi": null,
      "pe_volume": null
    },
    {
      "strike": 1040,
      "symbol_ce": "JSWSTEEL25NOV1040CE",
      "ce_token": 24584706,
      "ce_ltp": 0,
      "ce_oi": null,
      "ce_volume": null,
      "symbol_pe": "JSWSTEEL25NOV1040PE",
      "pe_token": 24584962,
      "pe_ltp": 0,
      "pe_oi": null,
      "pe_volume": null
    },
    {
      "strike": 1050,
      "symbol_ce": "JSWSTEEL25OCT1050CE",
      "ce_token": 24522754,
      "ce_ltp": 0,
      "ce_oi": null,
      "ce_volume": null,
      "symbol_pe": "JSWSTEEL25OCT1050PE",
      "pe_token": 24523010,
      "pe_ltp": 0,
      "pe_oi": null,
      "pe_volume": null
    },
    {
      "strike": 1060,
      "symbol_ce": "JSWSTEEL25NOV1060CE",
      "ce_token": 24585218,
      "ce_ltp": 0,
      "ce_oi": null,
      "ce_volume": null,
      "symbol_pe": "JSWSTEEL25NOV1060PE",
      "pe_token": 24585474,
      "pe_ltp": 0,
      "pe_oi": null,
      "pe_volume": null
    },
    {
      "strike": 1070,
      "symbol_ce": "JSWSTEEL25OCT1070CE",
      "ce_token": 24523266,
      "ce_ltp": 0,
      "ce_oi": null,
      "ce_volume": null,
      "symbol_pe": "JSWSTEEL25OCT1070PE",
      "pe_token": 24523522,
      "pe_ltp": 0,
      "pe_oi": null,
      "pe_volume": null
    },
    {
      "strike": 1080,
      "symbol_ce": "JSWSTEEL25NOV1080CE",
      "ce_token": 24585730,
      "ce_ltp": 0,
      "ce_oi": null,
      "ce_volume": null,
      "symbol_pe": "JSWSTEEL25NOV1080PE",
      "pe_token": 24585986,
      "pe_ltp": 0,
      "pe_oi": null,
      "pe_volume": null
    },
    {
      "strike": 1090,
      "symbol_ce": "JSWSTEEL25OCT1090CE",
      "ce_token": 24523778,
      "ce_ltp": 0,
      "ce_oi": null,
      "ce_volume": null,
      "symbol_pe": "JSWSTEEL25OCT1090PE",
      "pe_token": 24524034,
      "pe_ltp": 0,
      "pe_oi": null,
      "pe_volume": null
    },
    {
      "strike": 1100,
      "symbol_ce": "JSWSTEEL25NOV1100CE",
      "ce_token": 24586242,
      "ce_ltp": 0,
      "ce_oi": null,
      "ce_volume": null,
      "symbol_pe": "JSWSTEEL25NOV1100PE",
      "pe_token": 24586498,
      "pe_ltp": 0,
      "pe_oi": null,
      "pe_volume": null
    },
    {
      "strike": 1110,
      "symbol_ce": "JSWSTEEL25OCT1110CE",
      "ce_token": 24524290,
      "ce_ltp": 0,
      "ce_oi": null,
      "ce_volume": null,
      "symbol_pe": "JSWSTEEL25OCT1110PE",
      "pe_token": 24524546,
      "pe_ltp": 0,
      "pe_oi": null,
      "pe_volume": null
    },
    {
      "strike": 1120,
      "symbol_ce": "JSWSTEEL25NOV1120CE",
      "ce_token": 24586754,
      "ce_ltp": 0,
      "ce_oi": null,
      "ce_volume": null,
      "symbol_pe": "JSWSTEEL25NOV1120PE",
      "pe_token": 24587010,
      "pe_ltp": 0,
      "pe_oi": null,
      "pe_volume": null
    },
    {
      "strike": 1130,
      "symbol_ce": "JSWSTEEL25OCT1130CE",
      "ce_token": 24524802,
      "ce_ltp": 0,
      "ce_oi": null,
      "ce_volume": null,
      "symbol_pe": "JSWSTEEL25OCT1130PE",
      "pe_token": 24525058,
      "pe_ltp": 0,
      "pe_oi": null,
      "pe_volume": null
    },
    {
      "strike": 1140,
      "symbol_ce": "JSWSTEEL25OCT1140CE",
      "ce_token": 25863170,
      "ce_ltp": 0,
      "ce_oi": null,
      "ce_volume": null,
      "symbol_pe": "JSWSTEEL25OCT1140PE",
      "pe_token": 25863426,
      "pe_ltp": 0,
      "pe_oi": null,
      "pe_volume": null
    },
    {
      "strike": 1150,
      "symbol_ce": "JSWSTEEL25SEP1150CE",
      "ce_token": 25737986,
      "ce_ltp": 1.3,
      "ce_oi": null,
      "ce_volume": null,
      "symbol_pe": "JSWSTEEL25SEP1150PE",
      "pe_token": 25738242,
      "pe_ltp": 109.4,
      "pe_oi": null,
      "pe_volume": null
    },
    {
      "strike": 1160,
      "symbol_ce": "JSWSTEEL25NOV1160CE",
      "ce_token": 24587778,
      "ce_ltp": 0,
      "ce_oi": null,
      "ce_volume": null,
      "symbol_pe": "JSWSTEEL25NOV1160PE",
      "pe_token": 24588034,
      "pe_ltp": 0,
      "pe_oi": null,
      "pe_volume": null
    },
    {
      "strike": 1170,
      "symbol_ce": "JSWSTEEL25SEP1170CE",
      "ce_token": 25738498,
      "ce_ltp": 0.7,
      "ce_oi": null,
      "ce_volume": null,
      "symbol_pe": null,
      "pe_token": null,
      "pe_ltp": null,
      "pe_oi": null,
      "pe_volume": null
    },
    {
      "strike": 1180,
      "symbol_ce": "JSWSTEEL25SEP1180CE",
      "ce_token": 26537218,
      "ce_ltp": 0.8,
      "ce_oi": null,
      "ce_volume": null,
      "symbol_pe": null,
      "pe_token": null,
      "pe_ltp": null,
      "pe_oi": null,
      "pe_volume": null
    },
    {
      "strike": 1200,
      "symbol_ce": "JSWSTEEL25NOV1200CE",
      "ce_token": 24592386,
      "ce_ltp": 0,
      "ce_oi": null,
      "ce_volume": null,
      "symbol_pe": "JSWSTEEL25NOV1200PE",
      "pe_token": 24592642,
      "pe_ltp": 0,
      "pe_oi": null,
      "pe_volume": null
    },
    {
      "strike": 1220,
      "symbol_ce": "JSWSTEEL25SEP1220CE",
      "ce_token": 26538242,
      "ce_ltp": 4.95,
      "ce_oi": null,
      "ce_volume": null,
      "symbol_pe": null,
      "pe_token": null,
      "pe_ltp": null,
      "pe_oi": null,
      "pe_volume": null
    }
  ]
}