[{"Expiry":"29-May-2025","call_oi":748,"call_change_oi":58,"call_ltp":106.5,"strike_price":1400,"put_ltp":20.5,"put_oi":3108,"put_change_oi":356,"spot_price":1480.0,"tau":0.0908469051,"expiry_days":33,"rate":0.1,"atm_strike_price":1400,"is_atm_strike":"Y","call_iv":34.2,"put_iv":29.55,"call_delta":0.82,"put_delta":-0.17,"gamma":0.0028,"vega":1.116,"timestamp":0},{"Expiry":"26-Jun-2025","call_oi":0,"call_change_oi":0,"call_ltp":0.0,"strike_price":1400,"put_ltp":32.1,"put_oi":111,"put_change_oi":30,"spot_price":1480.0,"tau":0.1675592339,"expiry_days":61,"rate":0.1,"atm_strike_price":1400,"is_atm_strike":"Y","call_iv":0.0,"put_iv":27.68,"call_delta":0.0,"put_delta":-0.23,"gamma":0.0,"vega":0.0,"timestamp":0},{"Expiry":"31-Jul-2025","call_oi":0,"call_change_oi":0,"call_ltp":0.0,"strike_price":1400,"put_ltp":0.0,"put_oi":0,"put_change_oi":0,"spot_price":1480.0,"tau":0.2634496449,"expiry_days":96,"rate":0.1,"atm_strike_price":1400,"is_atm_strike":"Y","call_iv":0.0,"put_iv":0.0,"call_delta":0.0,"put_delta":0.0,"gamma":0.0,"vega":0.0,"timestamp":0},{"Expiry":"29-May-2025","call_oi":748,"call_change_oi":58,"call_ltp":106.5,"strike_price":1400,"put_ltp":20.5,"put_oi":3108,"put_change_oi":356,"spot_price":1480.0,"tau":0.0888971334,"expiry_days":32,"rate":0.1,"atm_strike_price":1400,"is_atm_strike":"Y","call_iv":34.71,"put_iv":30.01,"call_delta":0.83,"put_delta":-0.17,"gamma":0.0028,"vega":1.085,"timestamp":0},{"Expiry":"26-Jun-2025","call_oi":0,"call_change_oi":0,"call_ltp":0.0,"strike_price":1400,"put_ltp":32.1,"put_oi":111,"put_change_oi":30,"spot_price":1480.0,"tau":0.1656094622,"expiry_days":60,"rate":0.1,"atm_strike_price":1400,"is_atm_strike":"Y","call_iv":0.0,"put_iv":27.9,"call_delta":0.0,"put_delta":-0.23,"gamma":0.0,"vega":0.0,"timestamp":0},{"Expiry":"31-Jul-2025","call_oi":0,"call_change_oi":0,"call_ltp":0.0,"strike_price":1400,"put_ltp":0.0,"put_oi":0,"put_change_oi":0,"spot_price":1480.0,"tau":0.2614998732,"expiry_days":95,"rate":0.1,"atm_strike_price":1400,"is_atm_strike":"Y","call_iv":0.0,"put_iv":0.0,"call_delta":0.0,"put_delta":0.0,"gamma":0.0,"vega":0.0,"timestamp":0},{"Expiry":"29-May-2025","call_oi":759,"call_change_oi":11,"call_ltp":102.95,"strike_price":1400,"put_ltp":19.1,"put_oi":3154,"put_change_oi":46,"spot_price":1476.1,"tau":0.0861581684,"expiry_days":31,"rate":0.1,"atm_strike_price":1400,"is_atm_strike":"Y","call_iv":34.72,"put_iv":28.74,"call_delta":0.82,"put_delta":-0.17,"gamma":0.003,"vega":1.097,"timestamp":0},{"Expiry":"26-Jun-2025","call_oi":0,"call_change_oi":0,"call_ltp":0.0,"strike_price":1400,"put_ltp":34.85,"put_oi":109,"put_change_oi":-2,"spot_price":1476.1,"tau":0.1628704972,"expiry_days":59,"rate":0.1,"atm_strike_price":1400,"is_atm_strike":"Y","call_iv":0.0,"put_iv":28.93,"call_delta":0.0,"put_delta":-0.24,"gamma":0.0,"vega":0.0,"timestamp":0},{"Expiry":"31-Jul-2025","call_oi":0,"call_change_oi":0,"call_ltp":0.0,"strike_price":1400,"put_ltp":0.0,"put_oi":0,"put_change_oi":0,"spot_price":1476.1,"tau":0.2587609082,"expiry_days":94,"rate":0.1,"atm_strike_price":1400,"is_atm_strike":"Y","call_iv":0.0,"put_iv":0.0,"call_delta":0.0,"put_delta":0.0,"gamma":0.0,"vega":0.0,"timestamp":0},{"Expiry":"29-May-2025","call_oi":788,"call_change_oi":40,"call_ltp":104.6,"strike_price":1400,"put_ltp":18.4,"put_oi":3100,"put_change_oi":-8,"spot_price":1481.0,"tau":0.0854615043,"expiry_days":31,"rate":0.1,"atm_strike_price":1400,"is_atm_strike":"Y","call_iv":33.4,"put_iv":29.1,"call_delta":0.83,"put_delta":-0.16,"gamma":0.0028,"vega":1.042,"timestamp":0},{"Expiry":"26-Jun-2025","call_oi":0,"call_change_oi":0,"call_ltp":102.1,"strike_price":1400,"put_ltp":32.0,"put_oi":121,"put_change_oi":10,"spot_price":1481.0,"tau":0.1621738331,"expiry_days":59,"rate":0.1,"atm_strike_price":1400,"is_atm_strike":"Y","call_iv":23.32,"put_iv":28.23,"call_delta":0.76,"put_delta":-0.23,"gamma":0.0025,"vega":1.778,"timestamp":0},{"Expiry":"31-Jul-2025","call_oi":0,"call_change_oi":0,"call_ltp":0.0,"strike_price":1400,"put_ltp":0.0,"put_oi":0,"put_change_oi":0,"spot_price":1481.0,"tau":0.258064244,"expiry_days":94,"rate":0.1,"atm_strike_price":1400,"is_atm_strike":"Y","call_iv":0.0,"put_iv":0.0,"call_delta":0.0,"put_delta":0.0,"gamma":0.0,"vega":0.0,"timestamp":0},{"Expiry":"29-May-2025","call_oi":788,"call_change_oi":40,"call_ltp":104.6,"strike_price":1400,"put_ltp":18.4,"put_oi":3100,"put_change_oi":-8,"spot_price":1481.0,"tau":0.0851766553,"expiry_days":31,"rate":0.1,"atm_strike_price":1400,"is_atm_strike":"Y","call_iv":33.4,"put_iv":29.1,"call_delta":0.99,"put_delta":0.0,"gamma":0.0,"vega":0.001,"timestamp":0},{"Expiry":"31-Jul-2025","call_oi":0,"call_change_oi":0,"call_ltp":0.0,"strike_price":1400,"put_ltp":0.0,"put_oi":0,"put_change_oi":0,"spot_price":1481.0,"tau":0.257779395,"expiry_days":94,"rate":0.1,"atm_strike_price":1400,"is_atm_strike":"Y","call_iv":0.0,"put_iv":0.0,"call_delta":0.0,"put_delta":0.0,"gamma":0.0,"vega":0.0,"timestamp":0},{"Expiry":"29-May-2025","call_oi":3295,"call_change_oi":230,"call_ltp":32.2,"strike_price":1560,"put_ltp":22.5,"put_oi":2160,"put_change_oi":216,"spot_price":1567.3,"tau":0.0285616438,"expiry_days":10,"rate":0.1,"atm_strike_price":1560,"is_atm_strike":"Y","call_iv":27.59,"put_iv":25.23,"call_delta":0.71,"put_delta":-0.28,"gamma":0.0261,"vega":0.878,"timestamp":0},{"Expiry":"29-May-2025","call_oi":3824,"call_change_oi":-332,"call_ltp":37.6,"strike_price":1560,"put_ltp":8.6,"put_oi":1960,"put_change_oi":352,"spot_price":1585.9,"tau":0.0175862506,"expiry_days":6,"rate":0.1,"atm_strike_price":1560,"is_atm_strike":"Y","call_iv":27.8,"put_iv":23.36,"call_delta":0.99,"put_delta":-0.01,"gamma":0.0014,"vega":0.03,"timestamp":0},{"Expiry":"26-Jun-2025","call_oi":470,"call_change_oi":-68,"call_ltp":56.7,"strike_price":1560,"put_ltp":40.55,"put_oi":405,"put_change_oi":27,"spot_price":1585.9,"tau":0.0942985794,"expiry_days":34,"rate":0.1,"atm_strike_price":1560,"is_atm_strike":"Y","call_iv":22.48,"put_iv":27.62,"call_delta":0.85,"put_delta":-0.14,"gamma":0.009,"vega":1.06,"timestamp":0},{"Expiry":"31-Jul-2025","call_oi":0,"call_change_oi":0,"call_ltp":0.0,"strike_price":1560,"put_ltp":0.0,"put_oi":0,"put_change_oi":0,"spot_price":1585.9,"tau":0.1901889904,"expiry_days":69,"rate":0.1,"atm_strike_price":1560,"is_atm_strike":"Y","call_iv":0.0,"put_iv":0.0,"call_delta":0.0,"put_delta":0.0,"gamma":0.0,"vega":0.0,"timestamp":0},{"Expiry":"29-May-2025","call_oi":3339,"call_change_oi":-326,"call_ltp":28.25,"strike_price":1560,"put_ltp":8.3,"put_oi":1811,"put_change_oi":124,"spot_price":1579.8,"tau":0.0089914701,"expiry_days":3,"rate":0.1,"atm_strike_price":1560,"is_atm_strike":"Y","call_iv":29.1,"put_iv":28.77,"call_delta":1.0,"put_delta":0.0,"gamma":0.0012,"vega":0.012,"timestamp":0},{"Expiry":"26-Jun-2025","call_oi":730,"call_change_oi":227,"call_ltp":49.9,"strike_price":1560,"put_ltp":42.9,"put_oi":630,"put_change_oi":214,"spot_price":1579.8,"tau":0.0857037988,"expiry_days":31,"rate":0.1,"atm_strike_price":1560,"is_atm_strike":"Y","call_iv":21.72,"put_iv":28.81,"call_delta":0.8,"put_delta":-0.19,"gamma":0.0117,"vega":1.244,"timestamp":0},{"Expiry":"31-Jul-2025","call_oi":0,"call_change_oi":0,"call_ltp":0.0,"strike_price":1560,"put_ltp":0.0,"put_oi":0,"put_change_oi":0,"spot_price":1579.8,"tau":0.1815942098,"expiry_days":66,"rate":0.1,"atm_strike_price":1560,"is_atm_strike":"Y","call_iv":0.0,"put_iv":0.0,"call_delta":0.0,"put_delta":0.0,"gamma":0.0,"vega":0.0,"timestamp":0},{"Expiry":"29-May-2025","call_oi":3385,"call_change_oi":72,"call_ltp":17.75,"strike_price":1560,"put_ltp":11.85,"put_oi":2160,"put_change_oi":336,"spot_price":1562.7,"tau":0.006374778,"expiry_days":2,"rate":0.1,"atm_strike_price":1560,"is_atm_strike":"Y","call_iv":35.51,"put_iv":28.55,"call_delta":0.68,"put_delta":-0.32,"gamma":0.0618,"vega":0.413,"timestamp":0},{"Expiry":"26-Jun-2025","call_oi":1382,"call_change_oi":530,"call_ltp":43.6,"strike_price":1560,"put_ltp":49.75,"put_oi":1185,"put_change_oi":395,"spot_price":1562.7,"tau":0.0830871068,"expiry_days":30,"rate":0.1,"atm_strike_price":1560,"is_atm_strike":"Y","call_iv":23.86,"put_iv":28.85,"call_delta":0.55,"put_delta":-0.45,"gamma":0.0175,"vega":1.758,"timestamp":0},{"Expiry":"31-Jul-2025","call_oi":0,"call_change_oi":0,"call_ltp":0.0,"strike_price":1560,"put_ltp":0.0,"put_oi":0,"put_change_oi":0,"spot_price":1562.7,"tau":0.1789775178,"expiry_days":65,"rate":0.1,"atm_strike_price":1560,"is_atm_strike":"Y","call_iv":0.0,"put_iv":0.0,"call_delta":0.0,"put_delta":0.0,"gamma":0.0,"vega":0.0,"timestamp":0},{"Expiry":"26-Jun-2025","call_oi":1951,"call_change_oi":470,"call_ltp":39.5,"strike_price":1560,"put_ltp":40.15,"put_oi":1668,"put_change_oi":87,"spot_price":1553.5,"tau":0.066752949,"expiry_days":24,"rate":0.1,"atm_strike_price":1560,"is_atm_strike":"Y","call_iv":26.96,"put_iv":23.28,"call_delta":0.37,"put_delta":-0.62,"gamma":0.0189,"vega":1.5,"timestamp":0},{"Expiry":"31-Jul-2025","call_oi":33,"call_change_oi":0,"call_ltp":72.0,"strike_price":1560,"put_ltp":57.25,"put_oi":24,"put_change_oi":1,"spot_price":1553.5,"tau":0.16264336,"expiry_days":59,"rate":0.1,"atm_strike_price":1560,"is_atm_strike":"Y","call_iv":30.61,"put_iv":21.98,"call_delta":0.41,"put_delta":-0.57,"gamma":0.0123,"vega":2.404,"timestamp":0},{"Expiry":"28-Aug-2025","call_oi":0,"call_change_oi":0,"call_ltp":0.0,"strike_price":1560,"put_ltp":0.0,"put_oi":0,"put_change_oi":0,"spot_price":1553.5,"tau":0.2393556887,"expiry_days":87,"rate":0.1,"atm_strike_price":1560,"is_atm_strike":"Y","call_iv":0.0,"put_iv":0.0,"call_delta":0.0,"put_delta":0.0,"gamma":0.0,"vega":0.0,"timestamp":0},{"Expiry":"26-Jun-2025","call_oi":1945,"call_change_oi":464,"call_ltp":40.25,"strike_price":1560,"put_ltp":39.7,"put_oi":1717,"put_change_oi":136,"spot_price":1554.0,"tau":0.0665686834,"expiry_days":24,"rate":0.1,"atm_strike_price":1560,"is_atm_strike":"Y","call_iv":27.28,"put_iv":23.16,"call_delta":0.38,"put_delta":-0.61,"gamma":0.019,"vega":1.512,"timestamp":0},{"Expiry":"31-Jul-2025","call_oi":33,"call_change_oi":0,"call_ltp":72.0,"strike_price":1560,"put_ltp":57.25,"put_oi":24,"put_change_oi":1,"spot_price":1554.0,"tau":0.1624590944,"expiry_days":59,"rate":0.1,"atm_strike_price":1560,"is_atm_strike":"Y","call_iv":30.51,"put_iv":22.08,"call_delta":0.42,"put_delta":-0.56,"gamma":0.0124,"vega":2.412,"timestamp":0},{"Expiry":"28-Aug-2025","call_oi":0,"call_change_oi":0,"call_ltp":0.0,"strike_price":1560,"put_ltp":0.0,"put_oi":0,"put_change_oi":0,"spot_price":1554.0,"tau":0.2391714231,"expiry_days":87,"rate":0.1,"atm_strike_price":1560,"is_atm_strike":"Y","call_iv":0.0,"put_iv":0.0,"call_delta":0.0,"put_delta":0.0,"gamma":0.0,"vega":0.0,"timestamp":0},{"Expiry":"26-Jun-2025","call_oi":2098,"call_change_oi":617,"call_ltp":39.35,"strike_price":1560,"put_ltp":40.55,"put_oi":1855,"put_change_oi":274,"spot_price":1551.0,"tau":0.066256342,"expiry_days":24,"rate":0.1,"atm_strike_price":1560,"is_atm_strike":"Y","call_iv":27.63,"put_iv":22.71,"call_delta":0.33,"put_delta":-0.67,"gamma":0.0181,"vega":1.428,"timestamp":0},{"Expiry":"31-Jul-2025","call_oi":33,"call_change_oi":0,"call_ltp":73.15,"strike_price":1560,"put_ltp":59.9,"put_oi":29,"put_change_oi":6,"spot_price":1551.0,"tau":0.1621467529,"expiry_days":59,"rate":0.1,"atm_strike_price":1560,"is_atm_strike":"Y","call_iv":31.59,"put_iv":22.56,"call_delta":0.38,"put_delta":-0.6,"gamma":0.0121,"vega":2.355,"timestamp":0},{"Expiry":"28-Aug-2025","call_oi":0,"call_change_oi":0,"call_ltp":0.0,"strike_price":1560,"put_ltp":0.0,"put_oi":0,"put_change_oi":0,"spot_price":1551.0,"tau":0.2388590817,"expiry_days":87,"rate":0.1,"atm_strike_price":1560,"is_atm_strike":"Y","call_iv":0.0,"put_iv":0.0,"call_delta":0.0,"put_delta":0.0,"gamma":0.0,"vega":0.0,"timestamp":0},{"Expiry":"26-Jun-2025","call_oi":2686,"call_change_oi":579,"call_ltp":37.4,"strike_price":1560,"put_ltp":42.0,"put_oi":1963,"put_change_oi":109,"spot_price":1550.3,"tau":0.064266172,"expiry_days":23,"rate":0.1,"atm_strike_price":1560,"is_atm_strike":"Y","call_iv":27.17,"put_iv":23.9,"call_delta":0.31,"put_delta":-0.68,"gamma":0.0181,"vega":1.368,"timestamp":0},{"Expiry":"31-Jul-2025","call_oi":33,"call_change_oi":0,"call_ltp":0.0,"strike_price":1560,"put_ltp":60.0,"put_oi":30,"put_change_oi":0,"spot_price":1550.3,"tau":0.160156583,"expiry_days":58,"rate":0.1,"atm_strike_price":1560,"is_atm_strike":"Y","call_iv":0.0,"put_iv":22.64,"call_delta":0.0,"put_delta":-0.61,"gamma":0.0,"vega":0.0,"timestamp":0},{"Expiry":"28-Aug-2025","call_oi":0,"call_change_oi":0,"call_ltp":0.0,"strike_price":1560,"put_ltp":0.0,"put_oi":0,"put_change_oi":0,"spot_price":1550.3,"tau":0.2368689117,"expiry_days":86,"rate":0.1,"atm_strike_price":1560,"is_atm_strike":"Y","call_iv":0.0,"put_iv":0.0,"call_delta":0.0,"put_delta":0.0,"gamma":0.0,"vega":0.0,"timestamp":0},{"Expiry":"26-Jun-2025","call_oi":717,"call_change_oi":271,"call_ltp":47.0,"strike_price":1540,"put_ltp":32.85,"put_oi":1167,"put_change_oi":137,"spot_price":1549.0,"tau":0.064076484,"expiry_days":23,"rate":0.1,"atm_strike_price":1540,"is_atm_strike":"Y","call_iv":27.58,"put_iv":24.17,"call_delta":0.68,"put_delta":-0.32,"gamma":0.0183,"vega":1.38,"timestamp":0},{"Expiry":"26-Jun-2025","call_oi":717,"call_change_oi":271,"call_ltp":47.0,"strike_price":1540,"put_ltp":32.85,"put_oi":1167,"put_change_oi":137,"spot_price":1549.0,"tau":0.0639053146,"expiry_days":23,"rate":0.1,"atm_strike_price":1540,"is_atm_strike":"Y","call_iv":27.58,"put_iv":24.17,"call_delta":0.68,"put_delta":-0.32,"gamma":0.0183,"vega":1.38,"timestamp":1},{"Expiry":"26-Jun-2025","call_oi":1072,"call_change_oi":626,"call_ltp":43.55,"strike_price":1540,"put_ltp":34.55,"put_oi":1220,"put_change_oi":190,"spot_price":1543.4,"tau":0.0637645865,"expiry_days":23,"rate":0.1,"atm_strike_price":1540,"is_atm_strike":"Y","call_iv":27.28,"put_iv":23.61,"call_delta":0.57,"put_delta":-0.43,"gamma":0.0201,"vega":1.511,"timestamp":1748960},{"Expiry":"31-Jul-2025","call_oi":0,"call_change_oi":0,"call_ltp":0.0,"strike_price":1540,"put_ltp":0.0,"put_oi":0,"put_change_oi":0,"spot_price":1543.4,"tau":0.1596549975,"expiry_days":58,"rate":0.1,"atm_strike_price":1540,"is_atm_strike":"Y","call_iv":0.0,"put_iv":0.0,"call_delta":0.0,"put_delta":0.0,"gamma":0.0,"vega":0.0,"timestamp":1748960},{"Expiry":"26-Jun-2025","call_oi":4163,"call_change_oi":177,"call_ltp":36.85,"strike_price":1560,"put_ltp":26.85,"put_oi":2507,"put_change_oi":161,"spot_price":1568.0,"tau":0.052311295,"expiry_days":19,"rate":0.1,"atm_strike_price":1560,"is_atm_strike":"Y","call_iv":23.1,"put_iv":21.66,"call_delta":0.67,"put_delta":-0.32,"gamma":0.02,"vega":1.281,"timestamp":1749321900000},{"Expiry":"31-Jul-2025","call_oi":70,"call_change_oi":18,"call_ltp":69.0,"strike_price":1560,"put_ltp":50.0,"put_oi":44,"put_change_oi":3,"spot_price":1568.0,"tau":0.148201706,"expiry_days":54,"rate":0.1,"atm_strike_price":1560,"is_atm_strike":"Y","call_iv":27.49,"put_iv":22.78,"call_delta":0.6,"put_delta":-0.39,"gamma":0.0125,"vega":2.282,"timestamp":1749321900000},{"Expiry":"26-Jun-2025","call_oi":4163,"call_change_oi":177,"call_ltp":36.85,"strike_price":1560,"put_ltp":26.85,"put_oi":2507,"put_change_oi":161,"spot_price":1568.0,"tau":0.1455238458,"expiry_days":53,"rate":0.1,"atm_strike_price":1560,"is_atm_strike":"Y","call_iv":13.98,"put_iv":13.07,"call_delta":0.6,"put_delta":-0.38,"gamma":0.0127,"vega":2.26,"timestamp":"2025-08-18 23:47"},{"Expiry":"31-Jul-2025","call_oi":70,"call_change_oi":18,"call_ltp":69.0,"strike_price":1560,"put_ltp":50.0,"put_oi":44,"put_change_oi":3,"spot_price":1568.0,"tau":0.0496334348,"expiry_days":18,"rate":0.1,"atm_strike_price":1560,"is_atm_strike":"Y","call_iv":47.12,"put_iv":39.1,"call_delta":0.68,"put_delta":-0.32,"gamma":0.0205,"vega":1.24,"timestamp":"2025-08-18 23:47"},{"Expiry":"28-Aug-2025","call_oi":0,"call_change_oi":0,"call_ltp":0.0,"strike_price":1560,"put_ltp":0.0,"put_oi":0,"put_change_oi":0,"spot_price":1568.0,"tau":0.0270788623,"expiry_days":9,"rate":0.1,"atm_strike_price":1560,"is_atm_strike":"Y","call_iv":0.0,"put_iv":0.0,"call_delta":0.0,"put_delta":0.0,"gamma":0.0,"vega":0.0,"timestamp":"2025-08-18 23:47"}]