[{"Expiry":"29-May-2025","call_oi":1193,"call_change_oi":-91,"call_ltp":19.6,"strike_price":2080,"put_ltp":19.55,"put_oi":834,"put_change_oi":-291,"spot_price":2075.0,"tau":0.0063722095,"expiry_days":2,"rate":0.1,"atm_strike_price":2080,"is_atm_strike":"Y","call_iv":35.89,"put_iv":27.62,"call_delta":0.26,"put_delta":-0.74,"gamma":0.0421,"vega":0.496,"timestamp":0},{"Expiry":"26-Jun-2025","call_oi":106,"call_change_oi":11,"call_ltp":60.0,"strike_price":2080,"put_ltp":48.0,"put_oi":211,"put_change_oi":45,"spot_price":2075.0,"tau":0.0830845383,"expiry_days":30,"rate":0.1,"atm_strike_price":2080,"is_atm_strike":"Y","call_iv":26.51,"put_iv":19.3,"call_delta":0.43,"put_delta":-0.56,"gamma":0.0131,"vega":2.324,"timestamp":0},{"Expiry":"31-Jul-2025","call_oi":0,"call_change_oi":0,"call_ltp":0.0,"strike_price":2080,"put_ltp":68.3,"put_oi":6,"put_change_oi":3,"spot_price":2075.0,"tau":0.1789749493,"expiry_days":65,"rate":0.1,"atm_strike_price":2080,"is_atm_strike":"Y","call_iv":0.0,"put_iv":19.16,"call_delta":0.0,"put_delta":-0.53,"gamma":0.0,"vega":0.0,"timestamp":0},{"Expiry":"26-Jun-2025","call_oi":901,"call_change_oi":206,"call_ltp":43.25,"strike_price":2080,"put_ltp":46.7,"put_oi":530,"put_change_oi":-189,"spot_price":2065.1,"tau":0.0667514587,"expiry_days":24,"rate":0.1,"atm_strike_price":2080,"is_atm_strike":"Y","call_iv":23.89,"put_iv":18.45,"call_delta":0.29,"put_delta":-0.71,"gamma":0.0128,"vega":1.8,"timestamp":0},{"Expiry":"31-Jul-2025","call_oi":0,"call_change_oi":0,"call_ltp":0.0,"strike_price":2080,"put_ltp":0.0,"put_oi":8,"put_change_oi":0,"spot_price":2065.1,"tau":0.1626418696,"expiry_days":59,"rate":0.1,"atm_strike_price":2080,"is_atm_strike":"Y","call_iv":0.0,"put_iv":0.0,"call_delta":0.0,"put_delta":0.0,"gamma":0.0,"vega":0.0,"timestamp":0},{"Expiry":"26-Jun-2025","call_oi":216,"call_change_oi":77,"call_ltp":57.4,"strike_price":2040,"put_ltp":35.0,"put_oi":573,"put_change_oi":53,"spot_price":2050.6,"tau":0.0642685185,"expiry_days":23,"rate":0.1,"atm_strike_price":2040,"is_atm_strike":"Y","call_iv":25.53,"put_iv":19.68,"call_delta":0.66,"put_delta":-0.34,"gamma":0.0141,"vega":1.869,"timestamp":0},{"Expiry":"31-Jul-2025","call_oi":0,"call_change_oi":0,"call_ltp":0.0,"strike_price":2040,"put_ltp":50.0,"put_oi":0,"put_change_oi":0,"spot_price":2050.6,"tau":0.1601589295,"expiry_days":58,"rate":0.1,"atm_strike_price":2040,"is_atm_strike":"Y","call_iv":0.0,"put_iv":17.2,"call_delta":0.0,"put_delta":-0.39,"gamma":0.0,"vega":0.0,"timestamp":0},{"Expiry":"26-Jun-2025","call_oi":258,"call_change_oi":119,"call_ltp":58.15,"strike_price":2040,"put_ltp":33.45,"put_oi":597,"put_change_oi":77,"spot_price":2052.2,"tau":0.0640796233,"expiry_days":23,"rate":0.1,"atm_strike_price":2040,"is_atm_strike":"Y","call_iv":25.47,"put_iv":19.26,"call_delta":0.68,"put_delta":-0.31,"gamma":0.0137,"vega":1.819,"timestamp":0},{"Expiry":"31-Jul-2025","call_oi":0,"call_change_oi":0,"call_ltp":0.0,"strike_price":2040,"put_ltp":50.0,"put_oi":0,"put_change_oi":0,"spot_price":2052.2,"tau":0.1599700342,"expiry_days":58,"rate":0.1,"atm_strike_price":2040,"is_atm_strike":"Y","call_iv":0.0,"put_iv":17.43,"call_delta":0.0,"put_delta":-0.37,"gamma":0.0,"vega":0.0,"timestamp":0},{"Expiry":"28-Aug-2025","call_oi":0,"call_change_oi":0,"call_ltp":0.0,"strike_price":2040,"put_ltp":0.0,"put_oi":0,"put_change_oi":0,"spot_price":2052.2,"tau":0.236682363,"expiry_days":86,"rate":0.1,"atm_strike_price":2040,"is_atm_strike":"Y","call_iv":0.0,"put_iv":0.0,"call_delta":0.0,"put_delta":0.0,"gamma":0.0,"vega":0.0,"timestamp":0},{"Expiry":"26-Jun-2025","call_oi":258,"call_change_oi":119,"call_ltp":58.15,"strike_price":2040,"put_ltp":33.45,"put_oi":597,"put_change_oi":77,"spot_price":2052.2,"tau":0.0639286847,"expiry_days":23,"rate":0.1,"atm_strike_price":2040,"is_atm_strike":"Y","call_iv":25.47,"put_iv":19.26,"call_delta":0.68,"put_delta":-0.31,"gamma":0.0137,"vega":1.819,"timestamp":0},{"Expiry":"31-Jul-2025","call_oi":0,"call_change_oi":0,"call_ltp":0.0,"strike_price":2040,"put_ltp":50.0,"put_oi":0,"put_change_oi":0,"spot_price":2052.2,"tau":0.1598190956,"expiry_days":58,"rate":0.1,"atm_strike_price":2040,"is_atm_strike":"Y","call_iv":0.0,"put_iv":17.43,"call_delta":0.0,"put_delta":-0.37,"gamma":0.0,"vega":0.0,"timestamp":0},{"Expiry":"26-Jun-2025","call_oi":459,"call_change_oi":320,"call_ltp":48.5,"strike_price":2040,"put_ltp":40.35,"put_oi":931,"put_change_oi":411,"spot_price":2036.9,"tau":0.0637846588,"expiry_days":23,"rate":0.1,"atm_strike_price":2040,"is_atm_strike":"Y","call_iv":24.66,"put_iv":19.12,"call_delta":0.45,"put_delta":-0.54,"gamma":0.0154,"vega":2.014,"timestamp":1},{"Expiry":"31-Jul-2025","call_oi":0,"call_change_oi":0,"call_ltp":0.0,"strike_price":2040,"put_ltp":62.4,"put_oi":1,"put_change_oi":1,"spot_price":2036.9,"tau":0.1596750698,"expiry_days":58,"rate":0.1,"atm_strike_price":2040,"is_atm_strike":"Y","call_iv":0.0,"put_iv":19.08,"call_delta":0.0,"put_delta":-0.52,"gamma":0.0,"vega":0.0,"timestamp":1},{"Expiry":"28-Aug-2025","call_oi":0,"call_change_oi":0,"call_ltp":0.0,"strike_price":2040,"put_ltp":0.0,"put_oi":0,"put_change_oi":0,"spot_price":2036.9,"tau":0.2363873985,"expiry_days":86,"rate":0.1,"atm_strike_price":2040,"is_atm_strike":"Y","call_iv":0.0,"put_iv":0.0,"call_delta":0.0,"put_delta":0.0,"gamma":0.0,"vega":0.0,"timestamp":1},{"Expiry":"26-Jun-2025","call_oi":1390,"call_change_oi":-156,"call_ltp":34.4,"strike_price":2080,"put_ltp":37.8,"put_oi":1146,"put_change_oi":433,"spot_price":2072.0,"tau":0.0523111999,"expiry_days":19,"rate":0.1,"atm_strike_price":2080,"is_atm_strike":"Y","call_iv":20.35,"put_iv":17.91,"call_delta":0.37,"put_delta":-0.63,"gamma":0.0159,"vega":1.775,"timestamp":1749321900000},{"Expiry":"31-Jul-2025","call_oi":0,"call_change_oi":0,"call_ltp":0.0,"strike_price":2080,"put_ltp":79.9,"put_oi":28,"put_change_oi":0,"spot_price":2072.0,"tau":0.1482016109,"expiry_days":54,"rate":0.1,"atm_strike_price":2080,"is_atm_strike":"Y","call_iv":0.0,"put_iv":24.19,"call_delta":0.0,"put_delta":-0.57,"gamma":0.0,"vega":0.0,"timestamp":1749321900000},{"Expiry":"26-Jun-2025","call_oi":1390,"call_change_oi":-156,"call_ltp":34.4,"strike_price":2080,"put_ltp":37.8,"put_oi":1146,"put_change_oi":433,"spot_price":2072.0,"tau":0.0521305175,"expiry_days":19,"rate":0.1,"atm_strike_price":2080,"is_atm_strike":"Y","call_iv":20.35,"put_iv":17.91,"call_delta":0.37,"put_delta":-0.63,"gamma":0.0159,"vega":1.775,"timestamp":"2025-06-07 20:20"},{"Expiry":"31-Jul-2025","call_oi":0,"call_change_oi":0,"call_ltp":0.0,"strike_price":2080,"put_ltp":79.9,"put_oi":28,"put_change_oi":0,"spot_price":2072.0,"tau":0.1480209285,"expiry_days":54,"rate":0.1,"atm_strike_price":2080,"is_atm_strike":"Y","call_iv":0.0,"put_iv":24.19,"call_delta":0.0,"put_delta":-0.57,"gamma":0.0,"vega":0.0,"timestamp":"2025-06-07 20:20"}]