[{"Expiry":"29-May-2025","call_oi":6047,"call_change_oi":1570,"call_ltp":85.5,"strike_price":5500,"put_ltp":116.35,"put_oi":1860,"put_change_oi":167,"spot_price":5459.5,"tau":0.0175861872,"expiry_days":6,"rate":0.1,"atm_strike_price":5500,"is_atm_strike":"Y","call_iv":37.34,"put_iv":33.87,"call_delta":0.12,"put_delta":-0.87,"gamma":0.0059,"vega":1.44,"timestamp":"2025-05-23 10:56"},{"Expiry":"26-Jun-2025","call_oi":683,"call_change_oi":138,"call_ltp":239.3,"strike_price":5500,"put_ltp":242.0,"put_oi":663,"put_change_oi":62,"spot_price":5459.5,"tau":0.094298516,"expiry_days":34,"rate":0.1,"atm_strike_price":5500,"is_atm_strike":"Y","call_iv":39.19,"put_iv":33.5,"call_delta":0.31,"put_delta":-0.68,"gamma":0.0042,"vega":5.879,"timestamp":"2025-05-23 10:56"}]